fluidattacks_integrates_dal/__init__.py
fluidattacks_integrates_dal/_cli.py
fluidattacks_integrates_dal/_logger.py
fluidattacks_integrates_dal/_typing.py
fluidattacks_integrates_dal/client.py
fluidattacks_integrates_dal/core.py
fluidattacks_integrates_dal/list_groups.py
fluidattacks_integrates_dal/py.typed
fluidattacks_integrates_dal/utils.py
fluidattacks_integrates_dal/clients/__init__.py
fluidattacks_integrates_dal/clients/group/__init__.py
fluidattacks_integrates_dal/clients/organization/__init__.py
fluidattacks_integrates_dal-2.1.1.dist-info/entry_points.txt
fluidattacks_integrates_dal-2.1.1.dist-info/WHEEL
fluidattacks_integrates_dal-2.1.1.dist-info/METADATA
fluidattacks_integrates_dal-2.1.1.dist-info/RECORD
